orkera/__init__.py
orkera/client.py
orkera/models.py
orkera-0.4.0.dist-info/METADATA
orkera-0.4.0.dist-info/WHEEL
orkera-0.4.0.dist-info/top_level.txt
orkera-0.4.0.dist-info/RECORD
