Metadata-Version: 2.4
Name: orkera
Version: 0.4.0
Summary: Simple HTTP client for Orkera distributed task runner
Home-page: https://github.com/orkera/python-sdk
Author: Orkera Team
Author-email: contact@orkera.com
License: MIT
Project-URL: Bug Tracker, https://github.com/orkera/python-sdk/issues
Project-URL: Documentation, https://github.com/orkera/python-sdk
Project-URL: Source Code, https://github.com/orkera/python-sdk
Keywords: orkera,task,distributed,scheduler,async
Classifier: Development Status :: 3 - Alpha
Classifier: Intended Audience :: Developers
Classifier: License :: OSI Approved :: MIT License
Classifier: Programming Language :: Python :: 3
Classifier: Programming Language :: Python :: 3.7
Classifier: Programming Language :: Python :: 3.8
Classifier: Programming Language :: Python :: 3.9
Classifier: Programming Language :: Python :: 3.10
Classifier: Programming Language :: Python :: 3.11
Classifier: Programming Language :: Python :: 3.12
Classifier: Topic :: Software Development :: Libraries :: Python Modules
Classifier: Topic :: Internet :: WWW/HTTP :: HTTP Servers
Requires-Python: >=3.7
Requires-Dist: requests>=2.25.0
Requires-Dist: pydantic>=2.0.0
Dynamic: author
Dynamic: author-email
Dynamic: classifier
Dynamic: description
Dynamic: description-content-type
Dynamic: home-page
Dynamic: keywords
Dynamic: license
Dynamic: project-url
Dynamic: requires-dist
Dynamic: requires-python
Dynamic: summary
